sheetcraft/__init__.py
sheetcraft/format_fix.py
sheetcraft/formulas.py
sheetcraft/images.py
sheetcraft/jinja_ext.py
sheetcraft/styles.py
sheetcraft/template.py
sheetcraft/utils.py
sheetcraft/validation.py
sheetcraft/workbook.py
sheetcraft-0.2.5.dist-info/licenses/LICENSE
sheetcraft-0.2.5.dist-info/licenses/NOTICE
sheetcraft-0.2.5.dist-info/METADATA
sheetcraft-0.2.5.dist-info/WHEEL
sheetcraft-0.2.5.dist-info/top_level.txt
sheetcraft-0.2.5.dist-info/RECORD
