Metadata-Version: 2.4
Name: sheetcraft
Version: 0.2.5
Summary: Flexible, intuitive Excel processing library for .xlsx and .xls
Author-email: getaix <dev@getaix.tech>
License: Apache License
Project-URL: Homepage, https://github.com/getaix/sheetcraft
Project-URL: Repository, https://github.com/getaix/sheetcraft.git
Keywords: excel,xlsx,xls,openpyxl,xlsxwriter,xlwt,template,data validation,images
Classifier: Programming Language :: Python :: 3
Classifier: Programming Language :: Python :: 3 :: Only
Classifier: Programming Language :: Python :: 3.11
Classifier: Programming Language :: Python :: 3.12
Classifier: Programming Language :: Python :: 3.13
Classifier: Topic :: Software Development :: Libraries
Classifier: Intended Audience :: Developers
Classifier: License :: OSI Approved :: Apache Software License
Requires-Python: >=3.11
License-File: LICENSE
License-File: NOTICE
Requires-Dist: openpyxl>=3.1.2
Provides-Extra: images
Requires-Dist: Pillow>=9.0.0; extra == "images"
Provides-Extra: xls
Requires-Dist: xlwt>=1.3.0; extra == "xls"
Requires-Dist: xlrd==1.2.0; extra == "xls"
Provides-Extra: fast
Requires-Dist: XlsxWriter>=3.2.0; extra == "fast"
Provides-Extra: template
Requires-Dist: Jinja2>=3.1.2; extra == "template"
Provides-Extra: formula
Requires-Dist: numpy>=2.0.0; extra == "formula"
Provides-Extra: all
Requires-Dist: Pillow>=9.0.0; extra == "all"
Requires-Dist: xlwt>=1.3.0; extra == "all"
Requires-Dist: xlrd==1.2.0; extra == "all"
Requires-Dist: XlsxWriter>=3.2.0; extra == "all"
Requires-Dist: Jinja2>=3.1.2; extra == "all"
Requires-Dist: numpy>=2.0.0; extra == "all"
Provides-Extra: dev
Requires-Dist: pytest>=7.4.0; extra == "dev"
Requires-Dist: pytest-cov>=4.1.0; extra == "dev"
Requires-Dist: pytest-benchmark>=4.0.0; extra == "dev"
Dynamic: license-file
